nonebot_plugin_BotMailNotice/__init__.py
nonebot_plugin_botmailnotice-0.0.3.dist-info/LICENSE
nonebot_plugin_botmailnotice-0.0.3.dist-info/WHEEL
nonebot_plugin_botmailnotice-0.0.3.dist-info/METADATA
nonebot_plugin_botmailnotice-0.0.3.dist-info/RECORD
