Metadata-Version: 2.1
Name: nonebot-plugin-botmailnotice
Version: 0.0.3
Summary: 基于nonebot2bot断连时的Mail通知插件
Home-page: https://github.com/ZM25XC/BotMailNotice
License: MIT
Author: ZM25XC
Author-email: xingling25@qq.com
Requires-Python: >=3.8,<4.0
Classifier: License :: OSI Approved :: MIT License
Classifier: Programming Language :: Python :: 3
Classifier: Programming Language :: Python :: 3.8
Classifier: Programming Language :: Python :: 3.9
Classifier: Programming Language :: Python :: 3.10
Requires-Dist: aiosmtplib (>=2.0.0,<3.0.0)
Requires-Dist: nonebot2 (>=2.0.0,<3.0.0)
